shamsicalendar/__init__.py
shamsicalendar/shamsi_calendar.py
shamsicalendar-0.1.1.dist-info/licenses/LICENSE
shamsicalendar-0.1.1.dist-info/METADATA
shamsicalendar-0.1.1.dist-info/WHEEL
shamsicalendar-0.1.1.dist-info/top_level.txt
shamsicalendar-0.1.1.dist-info/RECORD
