Metadata-Version: 2.4
Name: ShamsiCalendar
Version: 0.1.1
Summary: Persian (Shamsi) Calendar and Date Entry for Python Tkinter
Home-page: https://github.com/p7deli/ShamsiCalendar
Author: Poriya Delavariyan
Author-email: poria.dell7@gmail.com
Classifier: Programming Language :: Python :: 3
Classifier: License :: OSI Approved :: MIT License
Classifier: Operating System :: OS Independent
Requires-Python: >=3.6
License-File: LICENSE
Requires-Dist: customtkinter
Requires-Dist: jdatetime
Dynamic: author
Dynamic: author-email
Dynamic: classifier
Dynamic: description
Dynamic: description-content-type
Dynamic: home-page
Dynamic: license-file
Dynamic: requires-dist
Dynamic: requires-python
Dynamic: summary
